setup.py
./assh/bin/assh
assh/__init__.py
assh/__main__.py
assh/assh.py
assh.egg-info/PKG-INFO
assh.egg-info/SOURCES.txt
assh.egg-info/dependency_links.txt
assh.egg-info/requires.txt
assh.egg-info/top_level.txt