Metadata-Version: 1.1
Name: assh
Version: 0.1.11
Summary: aws server list in ncurses - select your server/s and ssh to them
Home-page: http://github.com/ybrs/assh
Author: ybrs
Author-email: aybars.badur@gmail.com
License: MIT
Platform: UNKNOWN
Classifier: Development Status :: 4 - Beta
Classifier: Intended Audience :: Developers
Classifier: License :: OSI Approved :: MIT License
Classifier: Operating System :: OS Independent
Classifier: Programming Language :: Python
Classifier: Topic :: Database
Classifier: Topic :: Software Development :: Libraries :: Python Modules
